brighteyes_ffs/__init__.py
brighteyes_ffs/example.py
brighteyes_ffs/fcs/__init__.py
brighteyes_ffs/fcs/add_sum_column.py
brighteyes_ffs/fcs/align_lifetime_hist.py
brighteyes_ffs/fcs/arrivaltimes2filteredtimetrace.py
brighteyes_ffs/fcs/arrivaltimes2timetrace.py
brighteyes_ffs/fcs/atimes2corr.py
brighteyes_ffs/fcs/atimes2corrparallel.py
brighteyes_ffs/fcs/atimes2hist.py
brighteyes_ffs/fcs/atimes_data.py
brighteyes_ffs/fcs/bh_atimes2csv.py
brighteyes_ffs/fcs/binfile2arrivaltimes.py
brighteyes_ffs/fcs/binfile2data.py
brighteyes_ffs/fcs/corr2csv.py
brighteyes_ffs/fcs/corr_input_from_kw.py
brighteyes_ffs/fcs/data2phasor.py
brighteyes_ffs/fcs/detectors.py
brighteyes_ffs/fcs/distance2detelements.py
brighteyes_ffs/fcs/extract_spad_data.py
brighteyes_ffs/fcs/extract_spad_data_kw.py
brighteyes_ffs/fcs/extract_spad_photon_streams.py
brighteyes_ffs/fcs/fcs2arrivaltimes.py
brighteyes_ffs/fcs/fcs2corr.py
brighteyes_ffs/fcs/fcs2difftime.py
brighteyes_ffs/fcs/fcs_analytical.py
brighteyes_ffs/fcs/fcs_fit.py
brighteyes_ffs/fcs/fcs_load_g.py
brighteyes_ffs/fcs/fcs_polar.py
brighteyes_ffs/fcs/fcsbin2h5.py
brighteyes_ffs/fcs/fcsdata2video.py
brighteyes_ffs/fcs/filter_ap.py
brighteyes_ffs/fcs/filter_g.py
brighteyes_ffs/fcs/get_det_elem_from_array.py
brighteyes_ffs/fcs/get_fcs_info.py
brighteyes_ffs/fcs/imsd.py
brighteyes_ffs/fcs/lifetimehist.py
brighteyes_ffs/fcs/meas_to_analogcount.py
brighteyes_ffs/fcs/meas_to_count.py
brighteyes_ffs/fcs/mem_fit.py
brighteyes_ffs/fcs/plot_corrs_scheme.py
brighteyes_ffs/fcs/plot_fingerprint.py
brighteyes_ffs/fcs/plot_intensity_traces.py
brighteyes_ffs/fcs/plot_pycorrfit.py
brighteyes_ffs/fcs/read_bh_asc.py
brighteyes_ffs/fcs/read_bh_hist.py
brighteyes_ffs/fcs/read_bh_spc.py
brighteyes_ffs/fcs/read_binfile.py
brighteyes_ffs/fcs/select_g.py
brighteyes_ffs/fcs/spad_shifts.py
brighteyes_ffs/fcs/timetrace2corr.py
brighteyes_ffs/fcs/two_focus_fcs.py
brighteyes_ffs/fcs/u64_to_counts.py
brighteyes_ffs/fcs/w0_from_fingerprint.py
brighteyes_ffs-0.0.50.dist-info/licenses/LICENSE
brighteyes_ffs-0.0.50.dist-info/METADATA
brighteyes_ffs-0.0.50.dist-info/WHEEL
brighteyes_ffs-0.0.50.dist-info/top_level.txt
brighteyes_ffs-0.0.50.dist-info/RECORD
