Metadata-Version: 2.4
Name: brighteyes-ffs
Version: 0.0.50
Summary: Toolbox for analysing FCS/FFS data with array detectors
Author-email: Eli Slenders <eli.slenders@iit.it>
Project-URL: Homepage, https://github.com/VicidominiLab/brighteyes-ffs
Classifier: Programming Language :: Python :: 3
Classifier: License :: OSI Approved :: GNU General Public License v3 or later (GPLv3+)
Classifier: Operating System :: OS Independent
Requires-Python: >=3.7
License-File: LICENSE
Requires-Dist: h5py
Requires-Dist: joblib
Requires-Dist: matplotlib>=3.3.2
Requires-Dist: multipletau>=0.3.3
Requires-Dist: numpy>=1.19.4
Requires-Dist: pandas>=1.1.4
Requires-Dist: scipy
Requires-Dist: tifffile>=2020.9.29
Requires-Dist: seaborn
Requires-Dist: imutils
Requires-Dist: nbformat==5.8.0
Requires-Dist: PyQt5
Requires-Dist: qdarkstyle
Requires-Dist: ome_types
Requires-Dist: czifile
Requires-Dist: pydantic<2.0
Requires-Dist: brighteyes_ism
Requires-Dist: notebook==6.4.11
Requires-Dist: openpyxl
Requires-Dist: ptufile
Requires-Dist: libttp
Requires-Dist: jsonschema==4.17.3
Dynamic: license-file
